cli_interface_utils/__init__.py
cli_interface_utils/cli_input_controller.py
cli_interface_utils/cli_interface.py
cli_interface_utils/cli_word_processor.py
cli_interface_utils/cli_workers_controller.py
cli_interface_utils-0.1.dist-info/DESCRIPTION.rst
cli_interface_utils-0.1.dist-info/METADATA
cli_interface_utils-0.1.dist-info/RECORD
cli_interface_utils-0.1.dist-info/WHEEL
cli_interface_utils-0.1.dist-info/metadata.json
cli_interface_utils-0.1.dist-info/top_level.txt
cli_utils/__init__.py
cli_utils/cli_input_controller.py
cli_utils/cli_interface.py
cli_utils/cli_word_processor.py
cli_utils/cli_workers_controller.py
